pydantic_consul_settings/__init__.py
pydantic_consul_settings/consul_env.py
pydantic_consul_settings/version.py
pydantic_consul_settings-1.1.1.dist-info/LICENCE
pydantic_consul_settings-1.1.1.dist-info/METADATA
pydantic_consul_settings-1.1.1.dist-info/WHEEL
pydantic_consul_settings-1.1.1.dist-info/RECORD
