Metadata-Version: 2.1
Name: pydantic-consul-settings
Version: 1.1.1
Summary: Add Consul as source of env variable to settings
Home-page: https://github.com/jag-k/pydantic-consul-settings#readme
License: MIT
Author: Jag_k
Author-email: jag-k@users.noreply.github.com
Requires-Python: >=3.11,<4.0
Classifier: License :: OSI Approved :: MIT License
Classifier: Programming Language :: Python :: 3
Classifier: Programming Language :: Python :: 3.11
Classifier: Programming Language :: Python :: 3.12
Requires-Dist: pydantic (>=2,<3)
Requires-Dist: pydantic-settings (>=2,<3)
Requires-Dist: python-consul2 (>=0.1.5,<0.2.0)
Project-URL: Repository, https://github.com/jag-k/pydantic-consul-settings
